paws_acronym/paws_acronym.py
paws_acronym-0.3.0.dist-info/LICENSE
paws_acronym-0.3.0.dist-info/METADATA
paws_acronym-0.3.0.dist-info/WHEEL
paws_acronym-0.3.0.dist-info/entry_points.txt
paws_acronym-0.3.0.dist-info/top_level.txt
paws_acronym-0.3.0.dist-info/RECORD
