Metadata-Version: 2.1
Name: paws-acronym
Version: 0.3.0
Summary: Proper Acronyms With Synonyms, creates acronyms from a list of keywords
Home-page: https://github.com/guszejnovdavid/PAWS_acronym_generator
Author: David Guszejnov
Author-email: guszejnov.david@gmail.com
License: MIT
Platform: UNKNOWN
Requires-Dist: numpy
Requires-Dist: docopt
Requires-Dist: nltk
